{
    "coc.preferences.extensionUpdateCheck": "daily",
    "coc.preferences.formatOnType": true,
    "coc.preferences.formatOnSaveFiletypes": ["typescript", "css", "markdown", "javascript", "prisma"],
    "coc.preferences.maxFileSize": "20MB",
    "diagnostic.checkCurrentLine": true,
    "diagnostic.virtualText": true,
    "diagnostic.enableMessage": "jump",
    "diagnostic.errorSign": "✖",
    "diagnostic.warningSign": "⚠",
    "diagnostic.infoSign": "•",
    "diagnostic.hintSign": "•",
    "diagnostic-languageserver.mergeConfig": true,
    "git.enableGutters": true,
    "git.addedSign.text": "┃",
    "git.changedSign.text": "┃",
    "git.removedSign.text": "▁",
    "git.topRemovedSign.text": "▔",
    "git.changeRemovedSign.text": "▔",
    "prettier.requireConfig": true,
    "languageserver": {
        "graphql": {
            "command": "graphql-lsp",
            "args": ["server", "-m", "stream"],
            // customize filetypes to your needs
            "filetypes": ["typescript", "typescriptreact", "graphql"]
        },
        "dockerfile": {
            "command": "docker-langserver",
            "filetypes": ["dockerfile"],
            "args": ["--stdio"]
        },
        "terraform": {
            "command": "terraform-ls",
            "args": ["serve"],
            "filetypes": ["terraform", "tf"],
            "initializationOptions": {}
        }
    }
}
